KingLoki/__init__.py
KingLoki/proxy.cpython-313-darwin.so
KingLoki/proxy.pyi
KingLoki/workers.cpython-313-darwin.so
KingLoki/workers.pyi
KingLoki/cipher/__init__.py
KingLoki/cipher/_allciphers.cpython-313-darwin.so
KingLoki/cipher/_allciphers.pyi
KingLoki/cipher/_format.cpython-313-darwin.so
KingLoki/cipher/_format.pyi
KingLoki/loc/__init__.py
KingLoki/loc/detector.cpython-313-darwin.so
KingLoki/loc/localhost.cpython-313-darwin.so
KingLoki/loc/localhost.pyi
KingLoki/loc/scripts.cpython-313-darwin.so
KingLoki/loc/scripts.pyi
KingLoki/protocols/__init__.py
KingLoki/protocols/loki.cpython-313-darwin.so
KingLoki/protocols/loki.pyi
project_king_loki-0.0.3.dist-info/licenses/LICENSE.md
project_king_loki-0.0.3.dist-info/METADATA
project_king_loki-0.0.3.dist-info/WHEEL
project_king_loki-0.0.3.dist-info/top_level.txt
project_king_loki-0.0.3.dist-info/RECORD
